pycirclize/__init__.py
pycirclize/annotation.py
pycirclize/circos.py
pycirclize/config.py
pycirclize/patches.py
pycirclize/sector.py
pycirclize/tooltip.py
pycirclize/track.py
pycirclize/tree.py
pycirclize/parser/__init__.py
pycirclize/parser/bed.py
pycirclize/parser/genbank.py
pycirclize/parser/gff.py
pycirclize/parser/matrix.py
pycirclize/parser/table.py
pycirclize/utils/__init__.py
pycirclize/utils/dataset.py
pycirclize/utils/helper.py
pycirclize/utils/plot.py
pycirclize/utils/example_data/images/python_logo.png
pycirclize/utils/example_data/trees/alphabet.nwk
pycirclize/utils/example_data/trees/large_example.nwk
pycirclize/utils/example_data/trees/medium_example.nwk
pycirclize/utils/example_data/trees/small_example.nwk
pycirclize-1.10.0.dist-info/METADATA
pycirclize-1.10.0.dist-info/WHEEL
pycirclize-1.10.0.dist-info/licenses/LICENSE
pycirclize-1.10.0.dist-info/RECORD
