Metadata-Version: 2.4
Name: pyCirclize
Version: 1.10.0
Summary: Circular visualization in Python
Project-URL: homepage, https://moshi4.github.io/pyCirclize/
Project-URL: repository, https://github.com/moshi4/pyCirclize/
Author: moshi4
License-Expression: MIT
License-File: LICENSE
Keywords: bioinformatics,chord-diagram,circos,matplotlib,visualization
Classifier: Framework :: Matplotlib
Classifier: Intended Audience :: Science/Research
Classifier: Topic :: Scientific/Engineering :: Bio-Informatics
Requires-Python: >=3.10
Requires-Dist: biopython>=1.80
Requires-Dist: matplotlib>=3.6.3
Requires-Dist: numpy>=1.21
Requires-Dist: pandas>=1.3.5
Provides-Extra: tooltip
Requires-Dist: ipympl>=0.9.7; extra == 'tooltip'
